django_rls/__init__.py
django_rls/__version__.py
django_rls/apps.py
django_rls/backends/__init__.py
django_rls/backends/postgresql/__init__.py
django_rls/backends/postgresql/base.py
django_rls/conf.py
django_rls/db/__init__.py
django_rls/db/functions.py
django_rls/exceptions.py
django_rls/expressions.py
django_rls/management/__init__.py
django_rls/management/commands/__init__.py
django_rls/management/commands/disable_rls.py
django_rls/management/commands/enable_rls.py
django_rls/middleware.py
django_rls/migration_operations.py
django_rls/migrations/__init__.py
django_rls/models.py
django_rls/policies.py
django_rls/signals.py
django_rls/simple_context.py
django_rls-0.4.1.dist-info/METADATA
django_rls-0.4.1.dist-info/WHEEL
django_rls-0.4.1.dist-info/licenses/LICENSE
django_rls-0.4.1.dist-info/RECORD
