Metadata-Version: 2.4
Name: django-rls
Version: 0.4.1
Summary: PostgreSQL Row Level Security (RLS) for Django applications
License: BSD-3-Clause
License-File: LICENSE
Keywords: django,postgresql,rls,row-level-security,database,security,multi-tenant,saas
Author: Kuldeep Pisda
Author-email: kdpisda@gmail.com
Requires-Python: >=3.10,<4.0
Classifier: Development Status :: 3 - Alpha
Classifier: Environment :: Web Environment
Classifier: Framework :: Django
Classifier: Framework :: Django :: 5.0
Classifier: Framework :: Django :: 5.1
Classifier: Framework :: Django :: 5.2
Classifier: Framework :: Django :: 6.0
Classifier: Intended Audience :: Developers
Classifier: License :: OSI Approved :: BSD License
Classifier: Operating System :: OS Independent
Classifier: Programming Language :: Python
Classifier: Programming Language :: Python :: 3
Classifier: Programming Language :: Python :: 3.10
Classifier: Programming Language :: Python :: 3.11
Classifier: Programming Language :: Python :: 3.12
Classifier: Programming Language :: Python :: 3.13
Classifier: Programming Language :: Python :: 3.14
Classifier: Topic :: Database
Classifier: Topic :: Internet :: WWW/HTTP
Classifier: Topic :: Software Development :: Libraries :: Python Modules
Requires-Dist: Django (>=5.2,<7.0)
Project-URL: Documentation, https://django-rls.com
Project-URL: Homepage, https://github.com/kdpisda/django-rls
Project-URL: Repository, https://github.com/kdpisda/django-rls
